README.md
setup.py
sparkml_pipe.egg-info/PKG-INFO
sparkml_pipe.egg-info/SOURCES.txt
sparkml_pipe.egg-info/dependency_links.txt
sparkml_pipe.egg-info/requires.txt
sparkml_pipe.egg-info/top_level.txt
sparkmlpipe/__init__.py
sparkmlpipe/__version__.py
sparkmlpipe/sparkmlpipe.py
sparkmlpipe/mlpipe/__init__.py
sparkmlpipe/mlpipe/mlpipe_builder.py
sparkmlpipe/mlpipe/handler/__init__.py
sparkmlpipe/mlpipe/handler/base.py
sparkmlpipe/mlpipe/handler/feature.py
sparkmlpipe/mlpipe/handler/regression.py
sparkmlpipe/pipeline/__init__.py
sparkmlpipe/pipeline/base.py
sparkmlpipe/pipeline/classification.py
sparkmlpipe/pipeline/regression.py
sparkmlpipe/stats/__init__.py
sparkmlpipe/stats/base.py
sparkmlpipe/stats/correlation.py
sparkmlpipe/test/__init__.py
sparkmlpipe/test/test_ml.py
sparkmlpipe/test/test_ml_pipe.py
sparkmlpipe/test/test_stat.py
sparkmlpipe/utils/__init__.py
sparkmlpipe/utils/constants.py
sparkmlpipe/utils/dependencies.py
sparkmlpipe/utils/exceptions.py
sparkmlpipe/utils/logging_.py
sparkmlpipe/utils/pipeline.py
sparkmlpipe/utils/util.py