Metadata-Version: 1.0
Name: sparkml-pipe
Version: 0.2.2
Summary: A configurable PySpark pipeline library.
Home-page: https://bitbucket.org/xtechai/sparkml-pipe
Author: Michi Tech
Author-email: parkerzf@gmail.com
License: BSD
Platform: Linux
